uygavazifa123/__init__.py
uygavazifa123/main.py
uygavazifa123-0.0.1.dist-info/METADATA
uygavazifa123-0.0.1.dist-info/WHEEL
uygavazifa123-0.0.1.dist-info/top_level.txt
uygavazifa123-0.0.1.dist-info/RECORD
