Metadata-Version: 2.1
Name: uygavazifa123
Version: 0.0.1
Summary: Ob-havo malumotlari
Author: Java
Author-email: hdhdhdvojdcjbfbfhzjs@gmail.com
